dataflows_airtable/VERSION
dataflows_airtable/__init__.py
dataflows_airtable/consts.py
dataflows_airtable/dump_to_airtable.py
dataflows_airtable/load_from_airtable.py
dataflows_airtable/utilities.py
dataflows_airtable-0.2.5.dist-info/LICENSE
dataflows_airtable-0.2.5.dist-info/METADATA
dataflows_airtable-0.2.5.dist-info/WHEEL
dataflows_airtable-0.2.5.dist-info/top_level.txt
dataflows_airtable-0.2.5.dist-info/RECORD
